airpress/__init__.py
airpress/compressor.py
airpress/crypto.py
airpress-1.0.3.dist-info/LICENSE
airpress-1.0.3.dist-info/METADATA
airpress-1.0.3.dist-info/WHEEL
airpress-1.0.3.dist-info/top_level.txt
airpress-1.0.3.dist-info/RECORD
