Metadata-Version: 2.1
Name: airpress
Version: 1.0.3
Summary: A frustration-free compression tool for PKPass archives.
Home-page: https://github.com/captain-fox/airpress
Author: Stan Reduta
Author-email: stanislaw.reduta@gmail.com
License: MIT
Platform: UNKNOWN
Classifier: License :: OSI Approved :: MIT License
Classifier: Programming Language :: Python :: 3
Classifier: Programming Language :: Python :: 3.6
Classifier: Programming Language :: Python :: 3.7
Classifier: Programming Language :: Python :: 3.8
Classifier: Operating System :: OS Independent
Requires-Python: >=3.6
Requires-Dist: cryptography (>=2.9.2)
